{
  "updated_at": "2025-12-14T18:15:11.115Z",
  "items": [
    {
      "id": "7583038254560185633",
      "desc": "ambiance | #riderskill sur #Twitch",
      "cover": "https://p19-common-sign-useastred.tiktokcdn-eu.com/tos-useast2a-p-4864-euttp/owiX63AuEiwm9pmBiX0Y8BSAnII2zqOfoCgicA~tplv-tiktokx-cropcenter-q:300:400:q72.jpeg?dr=9232&refresh_token=273e6ad7&x-expires=1765821600&x-signature=LHNMjLLR%2B2I%2B%2BWfvrdA%2BIi8sW44%3D&t=bacd0480&ps=933b5bde&shp=d05b14bd&shcp=132edbea&idc=useast2b&biz_tag=tt_video&s=PUBLISH&sc=cover",
      "play": "https://v16m.tiktokcdn-eu.com/cece28c7b3bfc954451bfe3d0216406d/6940504c/video/tos/useast2a/tos-useast2a-ve-4864-euttp/oUvNuFvBDIhnc4v0EVFgmfBvhBfSpFDQEhQtwP/?a=1233&bti=MzU8OGYpNHYpNzo5ZjEuLjpkLTptNDQwOg%3D%3D&ch=0&cr=13&dr=0&er=0&lr=all&net=0&cd=0%7C0%7C0%7C&cv=1&br=1566&bt=783&cs=0&ds=6&ft=XsFbEqx4m~aPD120_Bhs3wULet3KaeF~O5&mime_type=video_mp4&qs=0&rc=NmZlaTY0Ozg4MzhoODUzO0BpM2p0Z3E5cmU4NzQzZjM2NUBiNTJfY14vNWMxNmMvMy9eYSNraWhkMmRzbnJhLS1kLTNzcw%3D%3D&vvpl=1&l=2025121502151035F2138808F3B0D566A7&btag=e00088000",
      "create_time": 1765563696,
      "stats": {
        "digg_count": 1,
        "comment_count": 0,
        "share_count": 0,
        "play_count": 259,
        "collect_count": 1
      }
    },
    {
      "id": "7580645864478149920",
      "desc": "[drops RUST on J-2]⚡️2K FULL ULTRA 😱🚀🔥 CHAOS TOTAL 🤖💥 | JE TENTE 😵🚨 | countdown drops rust in stream💀💰 | #riderskill sur #Twitch",
      "cover": "https://p19-common-sign-useastred.tiktokcdn-eu.com/tos-useast2a-p-4864-euttp/oIczfA1ikWBgCIPEcBipE3ABQ2m7vD1Yf9MwI8~tplv-tiktokx-cropcenter-q:300:400:q72.jpeg?dr=9232&refresh_token=b1bfc394&x-expires=1765821600&x-signature=t8yv%2B1myrG4%2Fu1Ab9xvr1Btkang%3D&t=bacd0480&ps=933b5bde&shp=d05b14bd&shcp=132edbea&idc=useast2b&biz_tag=tt_video&s=PUBLISH&sc=cover",
      "play": "https://v16m.tiktokcdn-eu.com/3e774cbc29c84cb830bcc36be1e8cf5b/6940504c/video/tos/useast2a/tos-useast2a-ve-4864-euttp/o0Azf5gZfJQmDrYAgDDStYDs3EGMFgfQA7FIY4/?a=1233&bti=M0BzMzU8OGYpNzo5Zi5wIzEuLjpkNDQwOg%3D%3D&ch=0&cr=13&dr=0&er=0&lr=all&net=0&cd=0%7C0%7C0%7C&cv=1&br=1630&bt=815&cs=0&ds=6&ft=XsFbEqx4m~aPD120_Bhs3wULet3KaeF~O5&mime_type=video_mp4&qs=0&rc=ZDM8OWczOTY5PGg6PDZpNEBpM3YzOHY5cnl3NzQzZjM2NUA0LjRfMTRiNl4xLS0vNmIvYSNvZGgtMmRzbm1hLS1kLTNzcw%3D%3D&vvpl=1&l=2025121502151035F2138808F3B0D566A7&btag=e00088000",
      "create_time": 1765006723,
      "stats": {
        "digg_count": 9,
        "comment_count": 0,
        "share_count": 1,
        "play_count": 311,
        "collect_count": 2
      }
    },
    {
      "id": "7576813130857106721",
      "desc": "omg j'ai survecu a l'enfer mdr ce clip merite un oscar ! | #riderskill sur #Twitch",
      "cover": "https://p19-common-sign-useastred.tiktokcdn-eu.com/tos-useast2a-p-4864-euttp/o4Uo9BfEakixBBpPYoxmIz06PwAckCkwiIRAAX~tplv-tiktokx-cropcenter-q:300:400:q72.jpeg?dr=9232&refresh_token=dc64c3eb&x-expires=1765821600&x-signature=f0M4tbfOG5KnUGjp8NQm94a%2BOlo%3D&t=bacd0480&ps=933b5bde&shp=d05b14bd&shcp=132edbea&idc=useast2b&s=PUBLISH&sc=cover&biz_tag=tt_video",
      "play": "https://v16m.tiktokcdn-eu.com/39f17e4d8c9f6b3c033c52f2d0103447/6940506a/video/tos/useast2a/tos-useast2a-ve-4864-euttp/owafKQzB0APxU5ciiHZx3CIoYBRmPkqoIAE7Mp/?a=1233&bti=M0BzMzU8OGYpNzo5Zi5wIzEuLjpkNDQwOg%3D%3D&ch=0&cr=13&dr=0&er=0&lr=all&net=0&cd=0%7C0%7C0%7C&cv=1&br=2016&bt=1008&cs=0&ds=6&ft=XsFbEqx4m~aPD120_Bhs3wULet3KaeF~O5&mime_type=video_mp4&qs=0&rc=ODdpNzU4O2hmZjc3Zmg0ZUBpM244NWs5cjw2NzQzZjM2NUBhYDE0MTEwNjAxYl5hXjFfYSNhbC9oMmQ0c2dhLS1kLTNzcw%3D%3D&vvpl=1&l=2025121502151035F2138808F3B0D566A7&btag=e00090000",
      "create_time": 1764114341,
      "stats": {
        "digg_count": 7,
        "comment_count": 2,
        "share_count": 0,
        "play_count": 341,
        "collect_count": 2
      }
    },
    {
      "id": "7576747888093547808",
      "desc": "rire brison , trahison , mais je joue encore | #riderskill sur #Twitch",
      "cover": "https://p19-common-sign-useastred.tiktokcdn-eu.com/tos-useast2a-p-4864-euttp/oYcmL5gTeJEV0hwUAGDSuCDeBIGMLgXdfAqImV~tplv-tiktokx-cropcenter-q:300:400:q72.jpeg?dr=9232&refresh_token=bd11040a&x-expires=1765821600&x-signature=dNKwEZ5YaHE%2Bk%2BQJQxeC7nDSUUU%3D&t=bacd0480&ps=933b5bde&shp=d05b14bd&shcp=132edbea&idc=useast2b&s=PUBLISH&sc=cover&biz_tag=tt_video",
      "play": "https://v16m.tiktokcdn-eu.com/10e66d713828ff66bf43fb1ac7bb86c3/6940504c/video/tos/useast2a/tos-useast2a-ve-4864-euttp/oAfd9HGLILJhE4DTeQIMJBgCGVAIeDcmSuCAg5/?a=1233&bti=MzU8OGYpNHYpNzo5ZjEuLjpkLTptNDQwOg%3D%3D&ch=0&cr=13&dr=0&er=0&lr=all&net=0&cd=0%7C0%7C0%7C&cv=1&br=1168&bt=584&cs=0&ds=6&ft=XsFbEqx4m~aPD120_Bhs3wULet3KaeF~O5&mime_type=video_mp4&qs=0&rc=Zzs0Ojo6N2c1ZmloNTppOEBpM3Zyd285cjwzNzQzZjM2NUA2MTA0LzEuNWAxYWIuMV41YSNzcW1jMmRjNWdhLS1kLTNzcw%3D%3D&vvpl=1&l=2025121502151035F2138808F3B0D566A7&btag=e00088000",
      "create_time": 1764099110,
      "stats": {
        "digg_count": 4,
        "comment_count": 1,
        "share_count": 0,
        "play_count": 308,
        "collect_count": 2
      }
    },
    {
      "id": "7576392566774533408",
      "desc": "depart imminent | #riderskill sur #Twitch",
      "cover": "https://p19-common-sign-useastred.tiktokcdn-eu.com/tos-useast2a-p-4864-euttp/oEtA2kiIuGLpxkzPYjBfw3oEBPC3iBBs0AC0mI~tplv-tiktokx-cropcenter-q:300:400:q72.jpeg?dr=9232&refresh_token=f26620e4&x-expires=1765821600&x-signature=%2BeEo1Ea%2FfSzawyHoza0GliXUj%2Bw%3D&t=bacd0480&ps=933b5bde&shp=d05b14bd&shcp=132edbea&idc=useast2b&biz_tag=tt_video&s=PUBLISH&sc=cover",
      "play": "https://v16m.tiktokcdn-eu.com/b8fb3bb24bd2936a1bbdc7f6a7e9bb60/6940504c/video/tos/useast2a/tos-useast2a-ve-4864-euttp/oMwBBQBRiDsfkwkzjAItCA0YL2uIEzQPo0mjyi/?a=1233&bti=MzU8OGYpNHYpNzo5ZjEuLjpkLTptNDQwOg%3D%3D&ch=0&cr=13&dr=0&er=0&lr=all&net=0&cd=0%7C0%7C0%7C&cv=1&br=1940&bt=970&cs=0&ds=6&ft=XsFbEqx4m~aPD120_Bhs3wULet3KaeF~O5&mime_type=video_mp4&qs=0&rc=OzhpNjZoN2k5OTRlaTs5aEBpamZ1cnA5cnlmNzQzZjM2NUA2NmI2Ni0xNi8xYi9gYWJjYSNqNnEyMmQ0LmZhLS1kLTNzcw%3D%3D&vvpl=1&l=2025121502151035F2138808F3B0D566A7&btag=e00088000",
      "create_time": 1764016381,
      "stats": {
        "digg_count": 4,
        "comment_count": 0,
        "share_count": 0,
        "play_count": 274,
        "collect_count": 2
      }
    },
    {
      "id": "7576391607264529696",
      "desc": "un nom que rien ne peut etteindre | #riderskill sur #Twitch",
      "cover": "https://p19-common-sign-useastred.tiktokcdn-eu.com/tos-useast2a-p-4864-euttp/okesJm3JGCDIydgRb0GvMSQDSIMAfgDuYL2gRf~tplv-tiktokx-cropcenter-q:300:400:q72.jpeg?dr=9232&refresh_token=eea4cbb9&x-expires=1765821600&x-signature=NpnqWh3zazANX4bezHDzGTr9oJY%3D&t=bacd0480&ps=933b5bde&shp=d05b14bd&shcp=132edbea&idc=useast2b&sc=cover&biz_tag=tt_video&s=PUBLISH",
      "play": "https://v16m.tiktokcdn-eu.com/1bfceb456ea18e5e4164034b295dd651/6940504c/video/tos/useast2a/tos-useast2a-ve-4864-euttp/ooHMvsIIQGgS3jSefgLMJyBd2EAsfgJRGDYDgb/?a=1233&bti=M0BzMzU8OGYpNzo5Zi5wIzEuLjpkNDQwOg%3D%3D&ch=0&cr=13&dr=0&er=0&lr=all&net=0&cd=0%7C0%7C0%7C&cv=1&br=1960&bt=980&cs=0&ds=6&ft=XsFbEqx4m~aPD120_Bhs3wULet3KaeF~O5&mime_type=video_mp4&qs=0&rc=M2U5NTM5NTs1ZDk5NGRkaEBpanFyOnA5cjlmNzQzZjM2NUAuMmE0NC1jX2AxYy9eLi4xYSNxcXJuMmRzLWZhLS1kLTNzcw%3D%3D&vvpl=1&l=2025121502151035F2138808F3B0D566A7&btag=e00088000",
      "create_time": 1764016156,
      "stats": {
        "digg_count": 2,
        "comment_count": 0,
        "share_count": 0,
        "play_count": 261,
        "collect_count": 2
      }
    },
    {
      "id": "7576391180921916705",
      "desc": "pres pour l'expédition ! a vos marque prés ..... | #riderskill sur #Twitch",
      "cover": "https://p19-common-sign-useastred.tiktokcdn-eu.com/tos-useast2a-p-4864-euttp/oUSgEkNgJGIjfgTGSvEDeL7g9GMmvIO9DXSfSB~tplv-tiktokx-cropcenter-q:300:400:q72.jpeg?dr=9232&refresh_token=e5a01560&x-expires=1765821600&x-signature=ee%2FNPrrspmkNl64Ls7uKVks5ma4%3D&t=bacd0480&ps=933b5bde&shp=d05b14bd&shcp=132edbea&idc=useast2b&biz_tag=tt_video&s=PUBLISH&sc=cover",
      "play": "https://v16m.tiktokcdn-eu.com/891e50792ea830c3b873bb91f9ea8e63/6940504c/video/tos/useast2a/tos-useast2a-ve-4864-euttp/oc9I8mNOGGvSfMfkwSLcg9EIDJgMQ5vegDDSmX/?a=1233&bti=MzU8OGYpNHYpNzo5ZjEuLjpkLTptNDQwOg%3D%3D&ch=0&cr=13&dr=0&er=0&lr=all&net=0&cd=0%7C0%7C0%7C&cv=1&br=1964&bt=982&cs=0&ds=6&ft=XsFbEqx4m~aPD120_Bhs3wULet3KaeF~O5&mime_type=video_mp4&qs=0&rc=Zjw8OjM8ZWVlaTRpZzg0ZEBpM2d5bnI5cmdlNzQzZjM2NUBhMTEzY2BeXjMxM2MxYDQwYSM2cnE0MmRzc2ZhLS1kLTNzcw%3D%3D&vvpl=1&l=2025121502151035F2138808F3B0D566A7&btag=e00088000",
      "create_time": 1764016056,
      "stats": {
        "digg_count": 4,
        "comment_count": 0,
        "share_count": 0,
        "play_count": 268,
        "collect_count": 2
      }
    },
    {
      "id": "7576361574517067040",
      "desc": "RIDERSKILL LES A CAPTé | #riderskill sur #Twitch",
      "cover": "https://p19-common-sign-useastred.tiktokcdn-eu.com/tos-useast2a-p-4864-euttp/oMwEgT4bILJevSAgIDrGMVcJUepymgSkPGneDM~tplv-tiktokx-cropcenter-q:300:400:q72.jpeg?dr=9232&refresh_token=1480023b&x-expires=1765821600&x-signature=HQIkaVIXOpRnl8VSphEqoKCcvXI%3D&t=bacd0480&ps=933b5bde&shp=d05b14bd&shcp=132edbea&idc=useast2b&biz_tag=tt_video&s=PUBLISH&sc=cover",
      "play": "https://v16m.tiktokcdn-eu.com/1e14d7feb9c52eb82422bd5cfaf290da/6940504c/video/tos/useast2a/tos-useast2a-ve-4864-euttp/oceSVomcDJIgQD7XgILbSpMGVeneJNUIGgDckE/?a=1233&bti=MzU8OGYpNHYpNzo5ZjEuLjpkLTptNDQwOg%3D%3D&ch=0&cr=13&dr=0&er=0&lr=all&net=0&cd=0%7C0%7C0%7C&cv=1&br=1708&bt=854&cs=0&ds=6&ft=XsFbEqx4m~aPD120_Bhs3wULet3KaeF~O5&mime_type=video_mp4&qs=0&rc=OjxnODVkZjY2Mzg0aGRlaUBpanhybnI5cmxkNzQzZjM2NUAtLS8zYi41XzIxMDYvXmExYSNhNnE0MmRrNmZhLS1kLTNzcw%3D%3D&vvpl=1&l=2025121502151035F2138808F3B0D566A7&btag=e00088000",
      "create_time": 1764009164,
      "stats": {
        "digg_count": 4,
        "comment_count": 0,
        "share_count": 0,
        "play_count": 251,
        "collect_count": 2
      }
    },
    {
      "id": "7576361284271213856",
      "desc": "... | #riderskill sur #Twitch",
      "cover": "https://p19-common-sign-useastred.tiktokcdn-eu.com/tos-useast2a-p-4864-euttp/ooEkIADcBpCJEvDpKFACffTlYSnwLEyQmjKIBw~tplv-tiktokx-cropcenter-q:300:400:q72.jpeg?dr=9232&refresh_token=a4588482&x-expires=1765821600&x-signature=jf4m6WRcgoPbOxR0N67EduXDapg%3D&t=bacd0480&ps=933b5bde&shp=d05b14bd&shcp=132edbea&idc=useast2b&biz_tag=tt_video&s=PUBLISH&sc=cover",
      "play": "https://v16m.tiktokcdn-eu.com/a66811eb1f471b95d23914be4b8b0804/6940504c/video/tos/useast2a/tos-useast2a-ve-4864-euttp/o8KSSgGwSJGp2eFJDOLIgkGXgSJDfrgIQVeHMU/?a=1233&bti=MzU8OGYpNHYpNzo5ZjEuLjpkLTptNDQwOg%3D%3D&ch=0&cr=13&dr=0&er=0&lr=all&net=0&cd=0%7C0%7C0%7C&cv=1&br=1772&bt=886&cs=0&ds=6&ft=XsFbEqx4m~aPD120_Bhs3wULet3KaeF~O5&mime_type=video_mp4&qs=0&rc=NmRpOjVoOjwzOzNpOGZnNEBpM3k4bm05cjVkNzQzZjM2NUAzNS4vMGFhNmIxNS9jLjUzYSNgMGhmMmRzNmZhLS1kLTNzcw%3D%3D&vvpl=1&l=2025121502151035F2138808F3B0D566A7&btag=e00088000",
      "create_time": 1764009100,
      "stats": {
        "digg_count": 3,
        "comment_count": 0,
        "share_count": 0,
        "play_count": 257,
        "collect_count": 2
      }
    },
    {
      "id": "7575615952708980000",
      "desc": "on lache rien | #riderskill sur #Twitch",
      "cover": "https://p19-common-sign-useastred.tiktokcdn-eu.com/tos-useast2a-p-4864-euttp/ooEAZG1IM1LfNCHeAAYDWYkqfhGFhTryIQeGBQ~tplv-tiktokx-cropcenter-q:300:400:q72.jpeg?dr=9232&refresh_token=98cb8a66&x-expires=1765821600&x-signature=lHBCx4aMMQMtjheQnulDMoksTKk%3D&t=bacd0480&ps=933b5bde&shp=d05b14bd&shcp=132edbea&idc=useast2b&biz_tag=tt_video&s=PUBLISH&sc=cover",
      "play": "https://v16m.tiktokcdn-eu.com/be592f6eefbb69456dac052c0146c60f/6940504c/video/tos/useast2a/tos-useast2a-ve-4864-euttp/oEiGGIA8gAkAKZAVRGHJIYLSWhYBfNefYsTe1H/?a=1233&bti=MzU8OGYpNHYpNzo5ZjEuLjpkLTptNDQwOg%3D%3D&ch=0&cr=13&dr=0&er=0&lr=all&net=0&cd=0%7C0%7C0%7C&cv=1&br=2474&bt=1237&cs=0&ds=6&ft=XsFbEqx4m~aPD120_Bhs3wULet3KaeF~O5&mime_type=video_mp4&qs=0&rc=ZTdpZTw0OjlmPGdoNmdnO0BpMzV2NHA5cjt5NzQzZjM2NUAvYWFfNjRiNi8xNDQ0MjIzYSMwMmEtMmRzcWRhLS1kLTNzcw%3D%3D&vvpl=1&l=2025121502151035F2138808F3B0D566A7&btag=e00088000",
      "create_time": 1763835556,
      "stats": {
        "digg_count": 4,
        "comment_count": 0,
        "share_count": 0,
        "play_count": 265,
        "collect_count": 2
      }
    },
    {
      "id": "7575597194464562464",
      "desc": "morning vibes | #riderskill sur #Twitch",
      "cover": "https://p19-common-sign-useastred.tiktokcdn-eu.com/tos-useast2a-p-4864-euttp/oU7Sh0QwaJtoHXZZBTUBgE1zAnstiPMEBB9iI~tplv-tiktokx-cropcenter-q:300:400:q72.jpeg?dr=9232&refresh_token=4ff294f3&x-expires=1765821600&x-signature=NP9tmKowrmUeuTJ%2FsTVaw5QegBE%3D&t=bacd0480&ps=933b5bde&shp=d05b14bd&shcp=132edbea&idc=useast2b&sc=cover&biz_tag=tt_video&s=PUBLISH",
      "play": "https://v16m.tiktokcdn-eu.com/5118c1b069a79398d4d2b47a4175ef87/6940504c/video/tos/useast2a/tos-useast2a-ve-4864-euttp/o0DQfE7g2I7QcFTgaMYfkopaWvGSDDgZhSQeJG/?a=1233&bti=MzU8OGYpNHYpNzo5ZjEuLjpkLTptNDQwOg%3D%3D&ch=0&cr=13&dr=0&er=0&lr=all&net=0&cd=0%7C0%7C0%7C&cv=1&br=1906&bt=953&cs=0&ds=6&ft=XsFbEqx4m~aPD120_Bhs3wULet3KaeF~O5&mime_type=video_mp4&qs=0&rc=aGU0ZWllZ2VpNjtpODQ5PEBpamdrZHc5cjp4NzQzZjM2NUAyLzYzYTBjNi8xXl9hMy80YSMxYy9qMmQ0b2RhLS1kLTNzcw%3D%3D&vvpl=1&l=2025121502151035F2138808F3B0D566A7&btag=e00088000",
      "create_time": 1763831197,
      "stats": {
        "digg_count": 3,
        "comment_count": 0,
        "share_count": 0,
        "play_count": 251,
        "collect_count": 2
      }
    },
    {
      "id": "7574118405935074592",
      "desc": "adios los santos | #riderskill sur #Twitch",
      "cover": "https://p19-common-sign-useastred.tiktokcdn-eu.com/tos-useast2a-p-4864-euttp/oMfKcEaIKmAtoEIpQHFfDBQYQriiy3EoBzDtwq~tplv-tiktokx-cropcenter-q:300:400:q72.jpeg?dr=9232&refresh_token=7c1dc459&x-expires=1765821600&x-signature=wpeoGcYD6pdqUsxtATDtMvChshM%3D&t=bacd0480&ps=933b5bde&shp=d05b14bd&shcp=132edbea&idc=useast2b&s=PUBLISH&sc=cover&biz_tag=tt_video",
      "play": "https://v16m.tiktokcdn-eu.com/e34816f6e634ce21e3164125b7f9cbef/6940504c/video/tos/useast2a/tos-useast2a-ve-4864-euttp/oUEQcFaqyHoLDrYCBffBKPwtQmE3DAJEQphoI3/?a=1233&bti=MzU8OGYpNHYpNzo5ZjEuLjpkLTptNDQwOg%3D%3D&ch=0&cr=13&dr=0&er=0&lr=all&net=0&cd=0%7C0%7C0%7C&cv=1&br=1168&bt=584&cs=0&ds=6&ft=XsFbEqx4m~aPD120_Bhs3wULet3KaeF~O5&mime_type=video_mp4&qs=0&rc=Zjc1ZmU6NWdmNzU5N2g2ZUBpamo0OnA5cmRkNzQzZjM2NUAzYWAxYy9fXmMxMzVhY2NeYSNvaHFuMmRrbWJhLS1kLTNzcw%3D%3D&vvpl=1&l=2025121502151035F2138808F3B0D566A7&btag=e00088000",
      "create_time": 1763486891,
      "stats": {
        "digg_count": 2,
        "comment_count": 0,
        "share_count": 0,
        "play_count": 254,
        "collect_count": 2
      }
    },
    {
      "id": "7573701219890384160",
      "desc": "... | #riderskill sur #Twitch",
      "cover": "https://p19-common-sign-useastred.tiktokcdn-eu.com/tos-useast2a-p-4864-euttp/o8MwpEZDQExBaF2FfNpBDAEtEobfUGIQzCM8Pm~tplv-tiktokx-cropcenter-q:300:400:q72.jpeg?dr=9232&refresh_token=3c9093cd&x-expires=1765821600&x-signature=U3WDMeJh5ejE4sAxS0h8K4celyE%3D&t=bacd0480&ps=933b5bde&shp=d05b14bd&shcp=132edbea&idc=useast2b&biz_tag=tt_video&s=PUBLISH&sc=cover",
      "play": "https://v16m.tiktokcdn-eu.com/113416ed121d4423ea2085d45014eac4/6940504c/video/tos/useast2a/tos-useast2a-ve-4864-euttp/oAeSNgGsQGDIIIbeegJgI8IL1m2FcyIKpCRDMY/?a=1233&bti=MzU8OGYpNHYpNzo5ZjEuLjpkLTptNDQwOg%3D%3D&ch=0&cr=13&dr=0&er=0&lr=all&net=0&cd=0%7C0%7C0%7C&cv=1&br=2216&bt=1108&cs=0&ds=6&ft=XsFbEqx4m~aPD120_Bhs3wULet3KaeF~O5&mime_type=video_mp4&qs=0&rc=ZjM0NDQ8Ozg5aWk1OjRoOkBpajdlOnA5cmptNzQzZjM2NUBfYGM2NTEyNi0xXjNjMjZiYSNgYG9uMmRrL2FhLS1kLTNzcw%3D%3D&vvpl=1&l=2025121502151035F2138808F3B0D566A7&btag=e00088000",
      "create_time": 1763389763,
      "stats": {
        "digg_count": 2,
        "comment_count": 0,
        "share_count": 0,
        "play_count": 273,
        "collect_count": 2
      }
    },
    {
      "id": "7573693768818298144",
      "desc": "... | #riderskill sur #Twitch",
      "cover": "https://p19-common-sign-useastred.tiktokcdn-eu.com/tos-useast2a-p-4864-euttp/o8qD2pp4AKB5E6wwFyEwCEIDbQTmGzfBRqf5n8~tplv-tiktokx-cropcenter-q:300:400:q72.jpeg?dr=9232&refresh_token=b781d5e1&x-expires=1765821600&x-signature=gT7D7e4UCGcos%2FXPjKS9RVZQy1k%3D&t=bacd0480&ps=933b5bde&shp=d05b14bd&shcp=132edbea&idc=useast2b&biz_tag=tt_video&s=PUBLISH&sc=cover",
      "play": "https://v16m.tiktokcdn-eu.com/dc30b108ecacce936bc41b8b13e603eb/6940504c/video/tos/useast2a/tos-useast2a-ve-4864-euttp/oEIaIBBpuGbKpFfG8REDoQQwm5DfE6wZ2EC4Ey/?a=1233&bti=MzU8OGYpNHYpNzo5ZjEuLjpkLTptNDQwOg%3D%3D&ch=0&cr=13&dr=0&er=0&lr=all&net=0&cd=0%7C0%7C0%7C&cv=1&br=1304&bt=652&cs=0&ds=6&ft=XsFbEqx4m~aPD120_Bhs3wULet3KaeF~O5&mime_type=video_mp4&qs=0&rc=Nzw5PDU6ZDMzMzU2Zjo3PEBpanNnOng5cnhsNzQzZjM2NUA1M14vNmM2XjAxLWMwNV8xYSM1czBgMmRraGFhLS1kLTNzcw%3D%3D&vvpl=1&l=2025121502151035F2138808F3B0D566A7&btag=e00088000",
      "create_time": 1763388026,
      "stats": {
        "digg_count": 3,
        "comment_count": 0,
        "share_count": 0,
        "play_count": 271,
        "collect_count": 2
      }
    },
    {
      "id": "7572971522055310625",
      "desc": "LOL | #riderskill sur #Twitch",
      "cover": "https://p19-common-sign-useastred.tiktokcdn-eu.com/tos-useast2a-p-4864-euttp/owKfDBfDmEtxBopwomUGMGGJYBZEKEmiFBARIQ~tplv-tiktokx-cropcenter-q:300:400:q72.jpeg?dr=9232&refresh_token=d6f63d80&x-expires=1765821600&x-signature=MEE%2FytzYfRtcXiFRgY80jswYNgE%3D&t=bacd0480&ps=933b5bde&shp=d05b14bd&shcp=132edbea&idc=useast2b&biz_tag=tt_video&s=PUBLISH&sc=cover",
      "play": "https://v16m.tiktokcdn-eu.com/f6c780f269c2b35d7f2fa4c2bbf98cef/69405049/video/tos/useast2a/tos-useast2a-ve-4864-euttp/o8IBYpow5BJILQBftBEEsFEDmmDjGGQuofGRZm/?a=1233&bti=MzU8OGYpNHYpNzo5ZjEuLjpkLTptNDQwOg%3D%3D&ch=0&cr=13&dr=0&er=0&lr=all&net=0&cd=0%7C0%7C0%7C&br=4864&bt=2432&cs=0&ds=6&ft=XsFbEqx4m~aPD120_Bhs3wULet3KaeF~O5&mime_type=video_mp4&qs=0&rc=Nzs3ZmY7Ozk8OGQzOjxlZ0BpMzk5OnA5cjc8NzQzZjM2NUAwMi9fNTJeNTAxNmI0NjJjYSMwZGxuMmRjZ2BhLS1kLTNzcw%3D%3D&vvpl=1&l=2025121502151035F2138808F3B0D566A7&btag=e000b8000",
      "create_time": 1763219859,
      "stats": {
        "digg_count": 3,
        "comment_count": 0,
        "share_count": 0,
        "play_count": 256,
        "collect_count": 2
      }
    },
    {
      "id": "7572918189470879009",
      "desc": "ouep | #riderskill sur #Twitch",
      "cover": "https://p19-common-sign-useastred.tiktokcdn-eu.com/tos-useast2a-p-4864-euttp/osFkgoJpGEm4DCEBEiLGwB0BmuwfQeUMwtGQID~tplv-tiktokx-cropcenter-q:300:400:q72.jpeg?dr=9232&refresh_token=106ee88c&x-expires=1765821600&x-signature=9A7VLeC7VZ%2B7P56B7Yu9AWbKsWI%3D&t=bacd0480&ps=933b5bde&shp=d05b14bd&shcp=132edbea&idc=useast2b&biz_tag=tt_video&s=PUBLISH&sc=cover",
      "play": "https://v16m.tiktokcdn-eu.com/4edad90f83d995d08f7085d74a3556ed/6940504c/video/tos/useast2a/tos-useast2a-ve-4864-euttp/ooTPlIBgWE0R1QZcxNEpDBpiBRqhaMaRiBcAY/?a=1233&bti=MzU8OGYpNHYpNzo5ZjEuLjpkLTptNDQwOg%3D%3D&ch=0&cr=13&dr=0&er=0&lr=all&net=0&cd=0%7C0%7C0%7C&cv=1&br=2636&bt=1318&cs=0&ds=6&ft=XsFbEqx4m~aPD120_Bhs3wULet3KaeF~O5&mime_type=video_mp4&qs=0&rc=NDtlOWQ6OjRpMzZoOzwzM0BpajQ8PGs5cjQ5NzQzZjM2NUAuMzYwNF8yXy8xYzEyY2JgYSMubGFfMmQ0ZmBhLS1kLTNzcw%3D%3D&vvpl=1&l=2025121502151035F2138808F3B0D566A7&btag=e00088000",
      "create_time": 1763207429,
      "stats": {
        "digg_count": 3,
        "comment_count": 0,
        "share_count": 0,
        "play_count": 271,
        "collect_count": 2
      }
    },
    {
      "id": "7571691290044157216",
      "desc": "et wesh gros sa ce passe comme sa avec riderskill | #riderskill sur #Twitch",
      "cover": "https://p19-common-sign-useastred.tiktokcdn-eu.com/tos-useast2a-p-4864-euttp/ocLBma0sBDAtiVxYigCY6EIBUoSziZWAw1fiSy~tplv-tiktokx-cropcenter-q:300:400:q72.jpeg?dr=9232&refresh_token=b3a8bb43&x-expires=1765821600&x-signature=58MRs3BV%2BusTvp%2FKtNAIJCcTeEA%3D&t=bacd0480&ps=933b5bde&shp=d05b14bd&shcp=132edbea&idc=useast2b&biz_tag=tt_video&s=PUBLISH&sc=cover",
      "play": "https://v16m.tiktokcdn-eu.com/26f777e31abfffd2d8e7dda2c830106b/6940504c/video/tos/useast2a/tos-useast2a-ve-4864-euttp/oMAkCDtiLiYJxYgQI0iByTfwEBUPoamsBzUVWA/?a=1233&bti=MzU8OGYpNHYpNzo5ZjEuLjpkLTptNDQwOg%3D%3D&ch=0&cr=13&dr=0&er=0&lr=all&net=0&cd=0%7C0%7C0%7C&cv=1&br=4920&bt=2460&cs=0&ds=6&ft=XsFbEqx4m~aPD120_Bhs3wULet3KaeF~O5&mime_type=video_mp4&qs=0&rc=PGdnOmhmNDg0Zzo8NDw4OEBpM2dzdWw5cmQzNzQzZjM2NUAzLi8uMWE1XzUxNV5iMV8wYSNsYTFsMmRzbl5hLS1kLTNzcw%3D%3D&vvpl=1&l=2025121502151035F2138808F3B0D566A7&btag=e00088000",
      "create_time": 1762921773,
      "stats": {
        "digg_count": 3,
        "comment_count": 0,
        "share_count": 1,
        "play_count": 272,
        "collect_count": 2
      }
    },
    {
      "id": "7571676181271956768",
      "desc": "reborn | #riderskill sur #Twitch",
      "cover": "https://p19-common-sign-useastred.tiktokcdn-eu.com/tos-useast2a-p-4864-euttp/oofADTCYeW7uTGYWfkuZGOAF7QIL8NNMQnf27T~tplv-tiktokx-cropcenter-q:300:400:q72.jpeg?dr=9232&refresh_token=0b646867&x-expires=1765821600&x-signature=IWtGLLnTkl03HdwiAeaDTxWcZ5M%3D&t=bacd0480&ps=933b5bde&shp=d05b14bd&shcp=132edbea&idc=useast2b&biz_tag=tt_video&s=PUBLISH&sc=cover",
      "play": "https://v16m.tiktokcdn-eu.com/641ef0abfea8cd04e30375976f16fff5/6940504c/video/tos/useast2a/tos-useast2a-ve-4864-euttp/oIIMkTguSfZfAGuech7NV7GTQgY3nNRQDA8WGf/?a=1233&bti=MzU8OGYpNHYpNzo5ZjEuLjpkLTptNDQwOg%3D%3D&ch=0&cr=13&dr=0&er=0&lr=all&net=0&cd=0%7C0%7C0%7C&cv=1&br=4664&bt=2332&cs=0&ds=6&ft=XsFbEqx4m~aPD120_Bhs3wULet3KaeF~O5&mime_type=video_mp4&qs=0&rc=NDc8ZTs3N2VoNjk5NTs5aUBpajl5cm85cnV5NzQzZjM2NUAuLjEtMzYtNjIxYDRfNS8wYSNvbzRvMmQ0cjZhLS1kLTNzcw%3D%3D&vvpl=1&l=2025121502151035F2138808F3B0D566A7&btag=e00088000",
      "create_time": 1762918254,
      "stats": {
        "digg_count": 2,
        "comment_count": 0,
        "share_count": 0,
        "play_count": 264,
        "collect_count": 2
      }
    },
    {
      "id": "7571509942218165526",
      "desc": "Merci pour tous vos Cadeaux et votre gratitude. Vous représentez beaucoup pour moi.",
      "cover": "https://p16-pu-sign-no.tiktokcdn-eu.com/tos-no1a-p-6123-no/oQ1QtFHdpEIpedLfXDEFkcwEILDA0YL8lAfMCz~tplv-tiktokx-cropcenter-q:300:400:q72.jpeg?dr=9232&refresh_token=38de3efe&x-expires=1765821600&x-signature=IIAY38osKOiqt2kVc9ebcHwwK04%3D&t=bacd0480&ps=933b5bde&shp=d05b14bd&shcp=132edbea&idc=useast2b&biz_tag=tt_video&s=PUBLISH&sc=cover",
      "play": "https://v16m.tiktokcdn-eu.com/89aac787828f4b642603e7221d4c2763/6940504e/video/tos/no1a/tos-no1a-ve-0068c001-no/oIkDDCiIE0IQEDFgpzwA0a2fmgpVBwCETIFpTe/?a=1233&bti=M0BzMzU8OGYpNzo5Zi5wIzEuLjpkNDQwOg%3D%3D&ch=0&cr=13&dr=0&er=0&lr=all&net=0&cd=0%7C0%7C0%7C&cv=1&br=1092&bt=546&cs=0&ds=6&ft=XsFbEqx4m~aPD120_Bhs3wULet3KaeF~O5&mime_type=video_mp4&qs=0&rc=NzplNzY6ZGhmOTs0Zzk3ZEBpamo8bG45cmZwNzMzbzgzNUA2XjQwNTQuXmIxM19jYzIvYSMucWNtMmQ0ZDZhLS1kLzFzcw%3D%3D&vvpl=1&l=2025121502151035F2138808F3B0D566A7&btag=e00088000",
      "create_time": 1762879536,
      "stats": {
        "digg_count": 3,
        "comment_count": 0,
        "share_count": 0,
        "play_count": 266,
        "collect_count": 2
      }
    },
    {
      "id": "7571509864636091670",
      "desc": "Merci pour tous vos Cadeaux et votre gratitude. Vous représentez beaucoup pour moi.",
      "cover": "https://p16-pu-sign-no.tiktokcdn-eu.com/tos-no1a-p-6123-no/o4waRLdBbIAUIEIpkEFfLDAYesQ4GwEJtkDoek~tplv-tiktokx-cropcenter-q:300:400:q72.jpeg?dr=9232&refresh_token=83fecfa6&x-expires=1765821600&x-signature=iIgt7bcrtxIuh0rQbI9sGgdDLSc%3D&t=bacd0480&ps=933b5bde&shp=d05b14bd&shcp=132edbea&idc=useast2b&s=PUBLISH&sc=cover&biz_tag=tt_video",
      "play": "https://v16m.tiktokcdn-eu.com/86ca90afc92238aa40d0210c0a5f2462/6940504e/video/tos/no1a/tos-no1a-ve-0068c001-no/okwTrtBUSIIBE2LpaDJF00AEE0DQmlAeeAf1CT/?a=1233&bti=MzU8OGYpNHYpNzo5ZjEuLjpkLTptNDQwOg%3D%3D&ch=0&cr=13&dr=0&er=0&lr=all&net=0&cd=0%7C0%7C0%7C&cv=1&br=948&bt=474&cs=0&ds=6&ft=XsFbEqx4m~aPD120_Bhs3wULet3KaeF~O5&mime_type=video_mp4&qs=0&rc=NGQ6MzM6NDw3aGlmPGU1Z0Bpamo8bG45cjpwNzMzbzgzNUA1LWJhNDIzXy0xL2NiMy4vYSMtcWNtMmRrZDZhLS1kLzFzcw%3D%3D&vvpl=1&l=2025121502151035F2138808F3B0D566A7&btag=e00088000",
      "create_time": 1762879518,
      "stats": {
        "digg_count": 3,
        "comment_count": 0,
        "share_count": 0,
        "play_count": 263,
        "collect_count": 2
      }
    },
    {
      "id": "7571394220150344992",
      "desc": "pret pour le prochain gta , je suis la , je suis pret | #riderskill sur #Twitch",
      "cover": "https://p19-common-sign-useastred.tiktokcdn-eu.com/tos-useast2a-p-4864-euttp/ok8EDf4iwElmQyf7OBpQFBAlIqBvEI9owDPhRP~tplv-tiktokx-cropcenter-q:300:400:q72.jpeg?dr=9232&refresh_token=67a02344&x-expires=1765821600&x-signature=fQiRw7OKm25VQ7ZZiRFtIu2bRaU%3D&t=bacd0480&ps=933b5bde&shp=d05b14bd&shcp=132edbea&idc=useast2b&biz_tag=tt_video&s=PUBLISH&sc=cover",
      "play": "https://v16m.tiktokcdn-eu.com/7ff52bbb41984d454942c53b2514b168/6940504c/video/tos/useast2a/tos-useast2a-ve-4864-euttp/ocDA1E4g8IfEiF7w7mrfgRHyQ9DoBBQOlpQvED/?a=1233&bti=MzU8OGYpNHYpNzo5ZjEuLjpkLTptNDQwOg%3D%3D&ch=0&cr=13&dr=0&er=0&lr=all&net=0&cd=0%7C0%7C0%7C&cv=1&br=1046&bt=523&cs=0&ds=6&ft=XsFbEqx4m~aPD120_Bhs3wULet3KaeF~O5&mime_type=video_mp4&qs=0&rc=NmYzMzZkZzVpZ2U3MzpoOUBpM3c2anY5cjtpNzQzZjM2NUAvNl4wMi1iX2ExYS5gX2IvYSNucS4wMmRrcjZhLS1kLTNzcw%3D%3D&vvpl=1&l=2025121502151035F2138808F3B0D566A7&btag=e00088000",
      "create_time": 1762852644,
      "stats": {
        "digg_count": 5,
        "comment_count": 0,
        "share_count": 0,
        "play_count": 263,
        "collect_count": 2
      }
    },
    {
      "id": "7571393240679697697",
      "desc": "adieu los santos | #riderskill sur #Twitch",
      "cover": "https://p19-common-sign-useastred.tiktokcdn-eu.com/tos-useast2a-p-4864-euttp/oon1IYeKbGTqfFb3afL1NGkBYAWA5GdSQCeJlI~tplv-tiktokx-cropcenter-q:300:400:q72.jpeg?dr=9232&refresh_token=4fae265c&x-expires=1765821600&x-signature=0G3Is2WYm5Gk%2FT1ePnfYJeIlfpI%3D&t=bacd0480&ps=933b5bde&shp=d05b14bd&shcp=132edbea&idc=useast2b&biz_tag=tt_video&s=PUBLISH&sc=cover",
      "play": "https://v16m.tiktokcdn-eu.com/8925cc49784ac7af529a2ef6a9623bc3/6940504c/video/tos/useast2a/tos-useast2a-ve-4864-euttp/o82b11geQI5CUKDNffkAlGrGSIEFYWqeATKLwG/?a=1233&bti=MzU8OGYpNHYpNzo5ZjEuLjpkLTptNDQwOg%3D%3D&ch=0&cr=13&dr=0&er=0&lr=all&net=0&cd=0%7C0%7C0%7C&cv=1&br=1000&bt=500&cs=0&ds=6&ft=XsFbEqx4m~aPD120_Bhs3wULet3KaeF~O5&mime_type=video_mp4&qs=0&rc=ZmlkODpnNDxmMzs8MzxmOEBpamg1O3c5cmVpNzQzZjM2NUBhLi41L15gXjUxXjZiXi5gYSNjX142MmRjcTZhLS1kLTNzcw%3D%3D&vvpl=1&l=2025121502151035F2138808F3B0D566A7&btag=e00088000",
      "create_time": 1762852526,
      "stats": {
        "digg_count": 2,
        "comment_count": 0,
        "share_count": 0,
        "play_count": 279,
        "collect_count": 2
      }
    },
    {
      "id": "7571043374233373985",
      "desc": "oulalalala | #riderskill sur #Twitch",
      "cover": "https://p19-common-sign-useastred.tiktokcdn-eu.com/tos-useast2a-p-4864-euttp/oUHLMZlGEigRqI3AbSAiABAIABaw0syBvT1R0~tplv-tiktokx-cropcenter-q:300:400:q72.jpeg?dr=9232&refresh_token=ad9a75ac&x-expires=1765821600&x-signature=0QmeVu%2Br38AR0pelGa7eBdXtF%2B0%3D&t=bacd0480&ps=933b5bde&shp=d05b14bd&shcp=132edbea&idc=useast2b&biz_tag=tt_video&s=PUBLISH&sc=cover",
      "play": "https://v16m.tiktokcdn-eu.com/cc4dbafab43e7b9c638f756493cb07ee/6940504c/video/tos/useast2a/tos-useast2a-ve-4864-euttp/owABQE00A3BAHQ1ZJJQ8MIaAw6RqagTiAyiRv/?a=1233&bti=MzU8OGYpNHYpNzo5ZjEuLjpkLTptNDQwOg%3D%3D&ch=0&cr=13&dr=0&er=0&lr=all&net=0&cd=0%7C0%7C0%7C&cv=1&br=5048&bt=2524&cs=0&ds=6&ft=XsFbEqx4m~aPD120_Bhs3wULet3KaeF~O5&mime_type=video_mp4&qs=0&rc=NDllaWRkODk6ZTc7MzpkZUBpM2xod245cjN2NzQzZjM2NUAyLzNiYzBeNV4xX14zNjAvYSMtaW5uMmRrLTVhLS1kLTNzcw%3D%3D&vvpl=1&l=2025121502151035F2138808F3B0D566A7&btag=e00088000",
      "create_time": 1762770948,
      "stats": {
        "digg_count": 3,
        "comment_count": 0,
        "share_count": 0,
        "play_count": 264,
        "collect_count": 2
      }
    },
    {
      "id": "7571030050489765153",
      "desc": "chill 3.0 | #riderskill sur #Twitch",
      "cover": "https://p19-common-sign-useastred.tiktokcdn-eu.com/tos-useast2a-p-4864-euttp/o82CsQKFjPkTuORZ46ITGLRAGNeGYAfYSIe4He~tplv-tiktokx-cropcenter-q:300:400:q72.jpeg?dr=9232&refresh_token=4a30ecd1&x-expires=1765821600&x-signature=6tnhT0%2B9FxOOM46iqEsF9mRq%2BlM%3D&t=bacd0480&ps=933b5bde&shp=d05b14bd&shcp=132edbea&idc=useast2b&biz_tag=tt_video&s=PUBLISH&sc=cover",
      "play": "https://v16m.tiktokcdn-eu.com/f28b1eb5f9a2da1af5e296a24c4abf5d/6940504c/video/tos/useast2a/tos-useast2a-ve-4864-euttp/osgISZHegYPAY8RG9j9GeNcGfFTLAfsAgyEkR4/?a=1233&bti=MzU8OGYpNHYpNzo5ZjEuLjpkLTptNDQwOg%3D%3D&ch=0&cr=13&dr=0&er=0&lr=all&net=0&cd=0%7C0%7C0%7C&cv=1&br=4498&bt=2249&cs=0&ds=6&ft=XsFbEqx4m~aPD120_Bhs3wULet3KaeF~O5&mime_type=video_mp4&qs=0&rc=OTY3ZjQ2ZWg1Z2QzNDNnZ0BpanlsNm05cnJ1NzQzZjM2NUBiNDA0L2MvX18xMTYtYWI2YSNfMGRvMmRrNDVhLS1kLTNzcw%3D%3D&vvpl=1&l=2025121502151035F2138808F3B0D566A7&btag=e00088000",
      "create_time": 1762767844,
      "stats": {
        "digg_count": 3,
        "comment_count": 0,
        "share_count": 0,
        "play_count": 265,
        "collect_count": 2
      }
    }
  ]
}