{
  "updated_at": "2026-06-18T22:47:52.918Z",
  "items": [
    {
      "id": "uTOxEXueXPY",
      "title": "RUST : SURVIE &amp; CONSTRUCTION 🚀 Gameplay posé, entraide et échanges en direct ⚙️ Venez profi",
      "url": "https://www.youtube.com/watch?v=uTOxEXueXPY",
      "published_at": "2026-06-18T20:25:51+00:00",
      "cover": "https://i2.ytimg.com/vi/uTOxEXueXPY/hqdefault.jpg",
      "thumbnail": "https://i2.ytimg.com/vi/uTOxEXueXPY/hqdefault.jpg"
    },
    {
      "id": "R2AyOupR5wg",
      "title": "GTARP stream 2k FULLULTRA 5070TI 🎵_🎵1440p 🎧 chill 2.0 ambiance garantie ! 😎",
      "url": "https://www.youtube.com/watch?v=R2AyOupR5wg",
      "published_at": "2026-06-18T13:22:00+00:00",
      "cover": "https://i3.ytimg.com/vi/R2AyOupR5wg/hqdefault.jpg",
      "thumbnail": "https://i3.ytimg.com/vi/R2AyOupR5wg/hqdefault.jpg"
    },
    {
      "id": "ZPtTykGcLW8",
      "title": "Jour 6 : Je tabasse tout ce qui bouge 🔥 avec un niveau de skill  qui ferait passer Harry Potter p",
      "url": "https://www.youtube.com/watch?v=ZPtTykGcLW8",
      "published_at": "2026-06-18T10:41:52+00:00",
      "cover": "https://i3.ytimg.com/vi/ZPtTykGcLW8/hqdefault.jpg",
      "thumbnail": "https://i3.ytimg.com/vi/ZPtTykGcLW8/hqdefault.jpg"
    },
    {
      "id": "gmX5bN1It-o",
      "title": "SURVIE 🚀 Gameplay posé, entraide et échanges en direct ⚙️ Venez profiter d'un moment cool",
      "url": "https://www.youtube.com/watch?v=gmX5bN1It-o",
      "published_at": "2026-06-18T06:14:01+00:00",
      "cover": "https://i4.ytimg.com/vi/gmX5bN1It-o/hqdefault.jpg",
      "thumbnail": "https://i4.ytimg.com/vi/gmX5bN1It-o/hqdefault.jpg"
    },
    {
      "id": "dgeEj7gPLzs",
      "title": "Jour 4 : Plus je pratique, plus je crée de désastres... c'est peut-être ça,  (Part 1/2)",
      "url": "https://www.youtube.com/watch?v=dgeEj7gPLzs",
      "published_at": "2026-06-17T01:49:33+00:00",
      "cover": "https://i1.ytimg.com/vi/dgeEj7gPLzs/hqdefault.jpg",
      "thumbnail": "https://i1.ytimg.com/vi/dgeEj7gPLzs/hqdefault.jpg"
    },
    {
      "id": "mNqKplxVZ2k",
      "title": "Jour 5 : L'École des Sorciers💻🪄 : Montage PC Version Magique 🧪🛠️",
      "url": "https://www.youtube.com/watch?v=mNqKplxVZ2k",
      "published_at": "2026-06-17T01:49:27+00:00",
      "cover": "https://i2.ytimg.com/vi/mNqKplxVZ2k/hqdefault.jpg",
      "thumbnail": "https://i2.ytimg.com/vi/mNqKplxVZ2k/hqdefault.jpg"
    },
    {
      "id": "oYxzMlkvjOI",
      "title": "Jour 6 : Je tabasse tout ce qui bouge 🔥 avec un niveau de skill  qui ferait passer Harry Potter p",
      "url": "https://www.youtube.com/watch?v=oYxzMlkvjOI",
      "published_at": "2026-06-17T01:49:20+00:00",
      "cover": "https://i4.ytimg.com/vi/oYxzMlkvjOI/hqdefault.jpg",
      "thumbnail": "https://i4.ytimg.com/vi/oYxzMlkvjOI/hqdefault.jpg"
    },
    {
      "id": "IuXKZY0UbFU",
      "title": "Jour 5 : L'École des Sorciers💻🪄 : Montage PC Version Magique 🧪🛠️",
      "url": "https://www.youtube.com/watch?v=IuXKZY0UbFU",
      "published_at": "2026-06-17T01:49:17+00:00",
      "cover": "https://i2.ytimg.com/vi/IuXKZY0UbFU/hqdefault.jpg",
      "thumbnail": "https://i2.ytimg.com/vi/IuXKZY0UbFU/hqdefault.jpg"
    },
    {
      "id": "JMrfWrsJnwg",
      "title": "Jour 6 : Je tabasse tout ce qui bouge 🔥 avec un niveau de skill  qui f... | #riderskill sur #Twitch",
      "url": "https://www.youtube.com/watch?v=JMrfWrsJnwg",
      "published_at": "2026-06-16T17:09:28+00:00",
      "cover": "https://i3.ytimg.com/vi/JMrfWrsJnwg/hqdefault.jpg",
      "thumbnail": "https://i3.ytimg.com/vi/JMrfWrsJnwg/hqdefault.jpg"
    },
    {
      "id": "ijv3THTyR8w",
      "title": "Jour 4 : Plus je pratique, plus je crée de désastres... c'est peut-être ça,  (Part 2/2)",
      "url": "https://www.youtube.com/watch?v=ijv3THTyR8w",
      "published_at": "2026-06-16T02:42:29+00:00",
      "cover": "https://i2.ytimg.com/vi/ijv3THTyR8w/hqdefault.jpg",
      "thumbnail": "https://i2.ytimg.com/vi/ijv3THTyR8w/hqdefault.jpg"
    },
    {
      "id": "TRW5qwaJDH8",
      "title": "WzBot CLIP | Jour 5 : L'École des Sorciers💻🪄 : Montage PC Version Mag... | #riderskill sur #Twitch",
      "url": "https://www.youtube.com/watch?v=TRW5qwaJDH8",
      "published_at": "2026-06-15T21:53:56+00:00",
      "cover": "https://i1.ytimg.com/vi/TRW5qwaJDH8/hqdefault.jpg",
      "thumbnail": "https://i1.ytimg.com/vi/TRW5qwaJDH8/hqdefault.jpg"
    },
    {
      "id": "qxQYN1n1lGA",
      "title": "Jour 5 : L'École des Sorciers💻🪄 : Montage PC Version Magique 🧪🛠️ | #riderskill sur #Twitch",
      "url": "https://www.youtube.com/watch?v=qxQYN1n1lGA",
      "published_at": "2026-06-15T21:49:48+00:00",
      "cover": "https://i2.ytimg.com/vi/qxQYN1n1lGA/hqdefault.jpg",
      "thumbnail": "https://i2.ytimg.com/vi/qxQYN1n1lGA/hqdefault.jpg"
    },
    {
      "id": "XUNultB8d2k",
      "title": "Jour 5 : L'École des Sorciers💻🪄 : Montage PC Version Magique 🧪🛠️ | #riderskill sur #Twitch",
      "url": "https://www.youtube.com/watch?v=XUNultB8d2k",
      "published_at": "2026-06-15T20:54:50+00:00",
      "cover": "https://i1.ytimg.com/vi/XUNultB8d2k/hqdefault.jpg",
      "thumbnail": "https://i1.ytimg.com/vi/XUNultB8d2k/hqdefault.jpg"
    },
    {
      "id": "QhdclP13ueQ",
      "title": "Jour 5 : L'École des Sorciers💻🪄 : Montage PC Version Magique 🧪🛠️ | #riderskill sur #Twitch",
      "url": "https://www.youtube.com/watch?v=QhdclP13ueQ",
      "published_at": "2026-06-15T20:49:32+00:00",
      "cover": "https://i2.ytimg.com/vi/QhdclP13ueQ/hqdefault.jpg",
      "thumbnail": "https://i2.ytimg.com/vi/QhdclP13ueQ/hqdefault.jpg"
    },
    {
      "id": "JalOZE1fqKs",
      "title": "Jour 5 : L'École des Sorciers💻🪄 : Montage PC Version Magique 🧪🛠️ | #riderskill sur #Twitch",
      "url": "https://www.youtube.com/watch?v=JalOZE1fqKs",
      "published_at": "2026-06-15T20:29:51+00:00",
      "cover": "https://i3.ytimg.com/vi/JalOZE1fqKs/hqdefault.jpg",
      "thumbnail": "https://i3.ytimg.com/vi/JalOZE1fqKs/hqdefault.jpg"
    }
  ]
}